Metadata-Version: 1.0
Name: dhruvil-distributions
Version: 0.1
Summary: Gaussian and Binomial distributions
Home-page: UNKNOWN
Author: dhruvil karani
Author-email: karanidhruvil@gmail.com
License: UNKNOWN
Platform: UNKNOWN
